<columnTitles>
    <cell1>
        <cell lineHeight="25">
        </cell>
    </cell1>
<line1>
 <line lineHeight="0" >
    <cell1>
        <cell lineWidth="21">
        </cell>
    </cell1>
        <cell2>
            <cell lineWidth="79">
                <title align="C" border="1"  titleFontSizePt="11" titleFontStyle="B"  lineWidth='80' lineHeight='13'><text>Despesa</text></title>
            </cell>
        </cell2>
        <cell3>
            <cell  lineWidth="1" lineHeight="0"></cell>
        </cell3>
          <cell4>
            <cell lineWidth="26" >
                <title align="C" border="1" titleFontSizePt="11" titleFontStyle="B"   lineWidth='26' lineHeight='13'><text>Valor</text></title>
            </cell>
        </cell4>
        <cell6>
            <cell lineWidth="34" >
                <title align="C" border="1" titleFontSizePt="11" titleFontStyle="B"  lineWidth='34' lineHeight='13'><text>Data da Compra</text></title>
            </cell>
        </cell6>
        <cell7>
            <cell lineWidth="34" >
                <title align="C" border="1" titleFontSizePt="11" titleFontStyle="B"  lineWidth='34' lineHeight='13'><text>Data Vencimento</text></title>
            </cell>
        </cell7>
        <cell5>
            <cell lineWidth="50" >
                <title align="C" border="1" titleFontSizePt="11" titleFontStyle="B"   lineWidth='70' lineHeight='13'><text>Categoria</text></title>
            </cell>
        </cell5>
    </line>
</line1>
</columnTitles>